CHANGES.rst
MANIFEST.in
README.rst
setup.cfg
setup.py
docs/INSTALL.txt
docs/LICENSE.GPL
docs/LICENSE.txt
docs/TODO.txt
plone/__init__.py
plone.app.search.egg-info/PKG-INFO
plone.app.search.egg-info/SOURCES.txt
plone.app.search.egg-info/dependency_links.txt
plone.app.search.egg-info/entry_points.txt
plone.app.search.egg-info/namespace_packages.txt
plone.app.search.egg-info/not-zip-safe
plone.app.search.egg-info/requires.txt
plone.app.search.egg-info/top_level.txt
plone/app/__init__.py
plone/app/search/__init__.py
plone/app/search/browser.py
plone/app/search/configure.zcml
plone/app/search/search.js
plone/app/search/search.pt
plone/app/search/updated_search.pt
plone/app/search/profiles/default/jsregistry.xml
plone/app/search/profiles/default/metadata.xml
plone/app/search/tests/__init__.py
plone/app/search/tests/base.py
plone/app/search/tests/test_integration.py
plone/app/search/tests/performance/README.txt
plone/app/search/tests/performance/__init__.py
plone/app/search/tests/performance/test_search_performance.py
plone/app/search/tests/selenium/README.txt
plone/app/search/tests/selenium/__init__.py
plone/app/search/tests/selenium/test_selenium.py