Metadata-Version: 1.1
Name: plone.app.search
Version: 1.2.1
Summary: Search user interface for Plone CMS.
Home-page: http://github.com/plone/plone.app.search
Author: Denys Mishunov
Author-email: denys.mishunov@gmail.com
License: GPL
Platform: UNKNOWN
Classifier: Framework :: Plone
Classifier: Programming Language :: Python
Classifier: Topic :: Software Development :: Libraries :: Python Modules
